app_icon_creator/__init__.py
app_icon_creator/__main__.py
app_icon_creator-3.dist-info/LICENSE
app_icon_creator-3.dist-info/METADATA
app_icon_creator-3.dist-info/WHEEL
app_icon_creator-3.dist-info/top_level.txt
app_icon_creator-3.dist-info/RECORD
